managementdb/__init__.py
managementdb/add.py
managementdb/subtract.py
managementdb/extras/__init__.py
managementdb/extras/divide.py
managementdb/extras/multiply.py
managementdb-0.1.6.dist-info/METADATA
managementdb-0.1.6.dist-info/WHEEL
managementdb-0.1.6.dist-info/top_level.txt
managementdb-0.1.6.dist-info/RECORD
