Metadata-Version: 2.1
Name: managementdb
Version: 0.1.6
Summary: A package for MongoDB operations with logging
Author-email: Grenne <grenne@populisrh.com>
Project-URL: Homepage, https://your_project_homepage_url
Project-URL: Bug Tracker, https://your_bug_tracker_url
Project-URL: Source Code, https://your_source_code_repository_url
Classifier: Programming Language :: Python :: 3
Classifier: License :: OSI Approved :: MIT License
Classifier: Operating System :: OS Independent
Requires-Python: >=3.7
